nltko/__init__.py
nltko/_token/__init__.py
nltko/_token/base.py
nltko/_token/morph.py
nltko/_token/news.py
nltko/_token/token.py
nltko/utils/__init__.py
nltko/utils/base.py
nltko-0.0.2.dist-info/LICENSE
nltko-0.0.2.dist-info/METADATA
nltko-0.0.2.dist-info/WHEEL
nltko-0.0.2.dist-info/top_level.txt
nltko-0.0.2.dist-info/RECORD
