Metadata-Version: 2.1
Name: nltko
Version: 0.0.2
Summary: Personally tiny useful nltk of korean tips
Home-page: https://github.com/YongBeomKim/nltko
Author: momukji lab
Author-email: ybkim@momukji.com
License: The Unlicense
Keywords: pytip
Classifier: Programming Language :: Python :: 3.9
Classifier: Programming Language :: Python :: 3.10
Classifier: Programming Language :: Python :: 3.11
Requires-Python: >=3.6
License-File: LICENSE
Requires-Dist: nltk
Requires-Dist: tqdm
Requires-Dist: pytip
Requires-Dist: konlpy
Requires-Dist: kiwipiepy
